LICENSE
MANIFEST.in
README.md
requirements.txt
setup.cfg
setup.py
robotframework_guistatus.egg-info/PKG-INFO
robotframework_guistatus.egg-info/SOURCES.txt
robotframework_guistatus.egg-info/dependency_links.txt
robotframework_guistatus.egg-info/requires.txt
robotframework_guistatus.egg-info/top_level.txt
src/GuiStatus/GuiStatusApplication.py
src/GuiStatus/GuiStatusKeywords.py
src/GuiStatus/GuiStatusListener.py
src/GuiStatus/GuiStatusServer.py
src/GuiStatus/GuiStatusUI.py
src/GuiStatus/__init__.py
src/GuiStatus/logo.jpg
src/GuiStatus/version.py