Metadata-Version: 1.1
Name: robotframework-guistatus
Version: 0.0.1
Summary: Simple UI to show the status of currently running robot
Home-page: https://github.com/Omenia/robotframework-guistatus
Author: Jani Mikkonen
Author-email: jani.mikkonen@siili.com
License: Apache
Platform: UNKNOWN
Classifier: License :: OSI Approved :: Apache Software License
Classifier: Programming Language :: Python :: 2
Classifier: Programming Language :: Python :: 2.7
Classifier: Programming Language :: Python :: 3
Classifier: Programming Language :: Python :: 3.5
Classifier: Programming Language :: Python :: 3.6
Classifier: Programming Language :: Python :: 3.7
